[
  {"rank":1,  "title":"The Power Broker",                          "author":"Robert Caro",                "year":1974, "pages":1344},
  {"rank":2,  "title":"In Cold Blood",                             "author":"Truman Capote",              "year":1966, "pages":343},
  {"rank":3,  "title":"Night",                                     "author":"Elie Wiesel",                "year":1960, "pages":120},
  {"rank":4,  "title":"The Fire Next Time",                        "author":"James Baldwin",              "year":1963, "pages":106},
  {"rank":5,  "title":"Man's Search for Meaning",                  "author":"Viktor E. Frankl",           "year":1946, "pages":165},
  {"rank":6,  "title":"The Autobiography of Malcolm X",            "author":"Malcolm X",                  "year":1965, "pages":460},
  {"rank":7,  "title":"Pilgrim at Tinker Creek",                   "author":"Annie Dillard",              "year":1974, "pages":288},
  {"rank":8,  "title":"A Room of One's Own",                       "author":"Virginia Woolf",             "year":1929, "pages":112},
  {"rank":9,  "title":"Speak, Memory",                             "author":"Vladimir Nabokov",           "year":1951, "pages":268},
  {"rank":10, "title":"Hiroshima",                                 "author":"John Hersey",                "year":1946, "pages":196},
  {"rank":11, "title":"I Know Why the Caged Bird Sings",           "author":"Maya Angelou",               "year":1969, "pages":289},
  {"rank":12, "title":"Slouching Towards Bethlehem",               "author":"Joan Didion",                "year":1968, "pages":238},
  {"rank":13, "title":"The Electric Kool-Aid Acid Test",           "author":"Tom Wolfe",                  "year":1968, "pages":416},
  {"rank":14, "title":"The Souls of Black Folk",                   "author":"W.E.B. Du Bois",             "year":1903, "pages":224},
  {"rank":15, "title":"Silent Spring",                             "author":"Rachel Carson",              "year":1962, "pages":368},
  {"rank":16, "title":"Angela's Ashes",                            "author":"Frank McCourt",              "year":1996, "pages":364},
  {"rank":17, "title":"Black Boy",                                 "author":"Richard Wright",             "year":1945, "pages":419},
  {"rank":18, "title":"This Boy's Life",                           "author":"Tobias Wolff",               "year":1989, "pages":288},
  {"rank":19, "title":"Into Thin Air",                             "author":"Jon Krakauer",               "year":1997, "pages":332},
  {"rank":20, "title":"The Making of the Atomic Bomb",             "author":"Richard Rhodes",             "year":1986, "pages":886},
  {"rank":21, "title":"The Executioner's Song",                    "author":"Norman Mailer",              "year":1979, "pages":1056},
  {"rank":22, "title":"The Man Who Mistook His Wife for a Hat",    "author":"Oliver Sacks",               "year":1985, "pages":243},
  {"rank":23, "title":"West with the Night",                       "author":"Beryl Markham",              "year":1942, "pages":293},
  {"rank":24, "title":"The Spirit Catches You and You Fall Down",  "author":"Anne Fadiman",               "year":1997, "pages":341},
  {"rank":25, "title":"The Devil in the White City",               "author":"Erik Larson",                "year":2003, "pages":447},
  {"rank":26, "title":"Darkness Visible",                          "author":"William Styron",             "year":1990, "pages":84},
  {"rank":27, "title":"H Is for Hawk",                             "author":"Helen Macdonald",            "year":2014, "pages":300},
  {"rank":28, "title":"The Immortal Life of Henrietta Lacks",      "author":"Rebecca Skloot",             "year":2010, "pages":381},
  {"rank":29, "title":"The Warmth of Other Suns",                  "author":"Isabel Wilkerson",           "year":2010, "pages":622},
  {"rank":30, "title":"The Liars' Club",                           "author":"Mary Karr",                  "year":1995, "pages":320},
  {"rank":31, "title":"Meditations",                               "author":"Marcus Aurelius",            "year":180,  "pages":254},
  {"rank":32, "title":"The Road to Wigan Pier",                    "author":"George Orwell",              "year":1937, "pages":232},
  {"rank":33, "title":"The Guns of August",                        "author":"Barbara Tuchman",            "year":1962, "pages":511},
  {"rank":34, "title":"The Origins of Totalitarianism",            "author":"Hannah Arendt",              "year":1951, "pages":704},
  {"rank":35, "title":"The Myth of Sisyphus",                      "author":"Albert Camus",               "year":1942, "pages":212},
  {"rank":36, "title":"The Second Sex",                            "author":"Simone de Beauvoir",         "year":1949, "pages":800},
  {"rank":37, "title":"Between the World and Me",                  "author":"Ta-Nehisi Coates",           "year":2015, "pages":152},
  {"rank":38, "title":"Let Us Now Praise Famous Men",              "author":"James Agee",                 "year":1941, "pages":480},
  {"rank":39, "title":"The Wretched of the Earth",                 "author":"Frantz Fanon",               "year":1961, "pages":316},
  {"rank":40, "title":"A Civil Action",                            "author":"Jonathan Harr",              "year":1995, "pages":500},
  {"rank":41, "title":"The Emperor of All Maladies",               "author":"Siddhartha Mukherjee",       "year":2010, "pages":571},
  {"rank":42, "title":"The Snow Leopard",                          "author":"Peter Matthiessen",          "year":1978, "pages":294},
  {"rank":43, "title":"A Moveable Feast",                          "author":"Ernest Hemingway",           "year":1964, "pages":211},
  {"rank":44, "title":"The Diving Bell and the Butterfly",         "author":"Jean-Dominique Bauby",       "year":1997, "pages":144},
  {"rank":45, "title":"Just Kids",                                 "author":"Patti Smith",                "year":2010, "pages":278},
  {"rank":46, "title":"Endurance",                                 "author":"Alfred Lansing",             "year":1959, "pages":282},
  {"rank":47, "title":"Mountains Beyond Mountains",                "author":"Tracy Kidder",               "year":2003, "pages":317},
  {"rank":48, "title":"The Glass Castle",                          "author":"Jeannette Walls",            "year":2005, "pages":288},
  {"rank":49, "title":"Seabiscuit",                                "author":"Laura Hillenbrand",          "year":2001, "pages":399},
  {"rank":50, "title":"The Looming Tower",                         "author":"Lawrence Wright",            "year":2006, "pages":480}
]
